{"google":"","name":"iTopPage plugin for jQuery","note":"Don't delete this file! It's used internally to help with page regeneration.","tagline":"Showing a gradient box with a white arrow from a specified point, when user scrolling down to the bottom of the page.","body":"iTopPage plugin for jQuery\r\n==========================\r\nQ: Why iTopPage?\r\nA: Imageless \"Top of the page\" plugin for jQuery\r\n\r\nShowing a colored gradient box with a white arrow from a specified point,\r\nwhen user scrolling down to the bottom of the page.\r\n\r\nParameters:\r\n===========\r\n* startPosition: 100  \t\t//Position from top of the window (in pixels)\r\n* title: 'Scroll to Top'\t//Mouse hover title attribute text\r\n* color: 'red'\t\t\t\t//black(default),red,pink,blue,orange,green\r\n* place: 'bottomRight'\t\t//Position of the button: bottomLeft, bottomCenter, bottomRight(default)\r\n\r\nMust be use the jquery.itoppage.css file to format the button!\r\n\r\nUsage\r\n=====\r\n \t\t$(document).ready(function() {\r\n  \t\t\t$().iTopPage();\r\n  \t\t});\r\n  \t\t\r\n \t\t//or with parameters\r\n \t\t\r\n \t\t\r\n  \t\t$(document).ready(function() {\r\n  \t\t\t$().iTopPage({startPosition: 100, title: \"Oldal tetejére\"});\r\n  \t\t});\r\n\r\nToDo:\r\n=====\r\n\r\n* optional external image for \"top of the page\" button from parameters\r\n\r\nVersion:\r\n========\r\n1.2.2 (2013.01.22)\r\n* Can change the position of the button (bottomLeft, bottomCenter, bottomRight)\r\n\t\t\r\n1.1.2 (2013.01.22)\r\n* Can change gradient color of the button (black, red, orange, pink, blue, green)\r\n\r\n* Button position stabilized (absolute->fixed)\r\n* Code optimized\r\n\r\n1.0.0 (2013.01.21)\r\n \t\t\r\nLicense:\r\n========\r\nGPLv2\r\nhttp://www.gnu.org/licenses/gpl-2.0.html\r\n\r\nAuthor:\r\n=======\r\nBubori Attila\r\n \t\t\r\nContact:\r\n========\r\nbubori.attila@gmail.com"}